pyAudioKits/__init__.py
pyAudioKits/algorithm/__init__.py
pyAudioKits/algorithm/augment.py
pyAudioKits/algorithm/matching.py
pyAudioKits/algorithm/vad.py
pyAudioKits/analyse/__init__.py
pyAudioKits/analyse/freqDomainAnalyse.py
pyAudioKits/analyse/modelBasedAnalyse.py
pyAudioKits/analyse/timeDomainAnalyse.py
pyAudioKits/audio/__init__.py
pyAudioKits/audio/audio.py
pyAudioKits/audio/io.py
pyAudioKits/audio/simulate.py
pyAudioKits/datastructures/__init__.py
pyAudioKits/datastructures/axis.py
pyAudioKits/datastructures/ds.py
pyAudioKits/filters/__init__.py
pyAudioKits/filters/iirfilter.py
pyAudioKits/filters/manual.py
pyAudioKits/record/__init__.py
pyAudioKits/record/record.py
pyAudioKits-1.0.6.dist-info/LICENSE.txt
pyAudioKits-1.0.6.dist-info/METADATA
pyAudioKits-1.0.6.dist-info/WHEEL
pyAudioKits-1.0.6.dist-info/top_level.txt
pyAudioKits-1.0.6.dist-info/RECORD
