Metadata-Version: 2.1
Name: pyAudioKits
Version: 1.0.6
Summary: Powerful Python audio workflow support based on librosa and other libraries
Home-page: https://github.com/HarmoniaLeo/pyAudioKits
Author: HarmoniaLeo
Author-email: harmonialeo@gmail.com
Maintainer: HarmoniaLeo
Maintainer-email: harmonialeo@gmail.com
License: Public domain
Platform: any
Requires-Dist: scipy
Requires-Dist: playsound
Requires-Dist: librosa
Requires-Dist: numpy
Requires-Dist: SoundFile
Requires-Dist: Wave
Requires-Dist: matplotlib
Requires-Dist: seaborn
Requires-Dist: pandas
Requires-Dist: python-speech-features
Requires-Dist: hmmlearn
